ulogging/__init__.py
ulogging-1.1.0.dist-info/LICENSE
ulogging-1.1.0.dist-info/METADATA
ulogging-1.1.0.dist-info/WHEEL
ulogging-1.1.0.dist-info/top_level.txt
ulogging-1.1.0.dist-info/RECORD
